pcse/__init__.py
pcse/agromanager.py
pcse/decorators.py
pcse/engine.py
pcse/exceptions.py
pcse/fileinput.py
pcse/models.py
pcse/rerunner.py
pcse/signals.py
pcse/start_wofost.py
pcse/taskmanager.py
pcse/timer.py
pcse/traitlets.py
pcse/util.py
pcse/base/__init__.py
pcse/base/config_loader.py
pcse/base/dispatcher.py
pcse/base/engine.py
pcse/base/parameter_providers.py
pcse/base/simulationobject.py
pcse/base/states_rates.py
pcse/base/variablekiosk.py
pcse/base/weather.py
pcse/conf/Alcepas10_PP.conf
pcse/conf/FAO_WRSI.conf
pcse/conf/Lingra_NWLP_FD.conf
pcse/conf/Lingra_PP.conf
pcse/conf/Lingra_WLP_FD.conf
pcse/conf/Lintul3.conf
pcse/conf/Wofost72_PP.conf
pcse/conf/Wofost72_Pheno.conf
pcse/conf/Wofost72_WLP_CWB.conf
pcse/conf/Wofost73_PP.conf
pcse/conf/Wofost73_WLP_CWB.conf
pcse/conf/Wofost73_WLP_MLWB.conf
pcse/conf/Wofost81_NWLP_CWB_CNB.conf
pcse/conf/Wofost81_NWLP_MLWB_CNB.conf
pcse/conf/Wofost81_NWLP_MLWB_SNOMIN.conf
pcse/conf/Wofost81_PP.conf
pcse/conf/Wofost81_WLP_CWB.conf
pcse/conf/Wofost81_WLP_MLWB.conf
pcse/conf/Wofost_winterkill.conf
pcse/conf/__init__.py
pcse/crop/__init__.py
pcse/crop/abioticdamage.py
pcse/crop/alcepas.py
pcse/crop/assimilation.py
pcse/crop/evapotranspiration.py
pcse/crop/greenlayercrop.py
pcse/crop/leaf_dynamics.py
pcse/crop/lingra.py
pcse/crop/lingraN.py
pcse/crop/lingra_ndynamics.py
pcse/crop/lintul3.py
pcse/crop/n_dynamics.py
pcse/crop/npk_dynamics.py
pcse/crop/partitioning.py
pcse/crop/phenology.py
pcse/crop/respiration.py
pcse/crop/root_dynamics.py
pcse/crop/stem_dynamics.py
pcse/crop/storage_organ_dynamics.py
pcse/crop/wofost72.py
pcse/crop/wofost73.py
pcse/crop/wofost81.py
pcse/crop/wofost_winterkill.py
pcse/crop/nutrients/__init__.py
pcse/crop/nutrients/n_demand_uptake.py
pcse/crop/nutrients/n_stress.py
pcse/crop/nutrients/npk_demand_uptake.py
pcse/crop/nutrients/npk_stress.py
pcse/crop/nutrients/npk_translocation.py
pcse/input/__init__.py
pcse/input/cabo_reader.py
pcse/input/cabo_weather.py
pcse/input/csvweatherdataprovider.py
pcse-6.0.12.dist-info/licenses/LICENSE
pcse-6.0.12.dist-info/METADATA
pcse-6.0.12.dist-info/WHEEL
pcse-6.0.12.dist-info/top_level.txt
pcse-6.0.12.dist-info/RECORD
