Metadata-Version: 2.4
Name: pcse
Version: 6.0.12
Summary: PCSE is a framework for developing and runnning crop simulation models, it includes an implementation of the WOFOST and LINTUL crop simulation models and the LINGRA grassland simulation model.
Author-email: Allard de Wit <allard.dewit@wur.nl>, Herman Berghuijs <herman.berghuijs@wur.nl>
Maintainer-email: Allard de Wit <allard.dewit@wur.nl>, Herman Berghuijs <herman.berghuijs@wur.nl>
License-Expression: EUPL-1.2
Project-URL: Homepage, https://github.com/ajwdewit/pcse
Project-URL: documentation, https://pcse.readthedocs.io
Project-URL: repository, https://github.com/ajwdewit/pcse.git
Classifier: Programming Language :: Python :: 3
Classifier: Operating System :: OS Independent
Classifier: Development Status :: 5 - Production/Stable
Classifier: Environment :: Console
Classifier: Intended Audience :: Developers
Classifier: Intended Audience :: Science/Research
Classifier: Natural Language :: English
Classifier: Topic :: Scientific/Engineering
Requires-Python: >=3.9
License-File: LICENSE
Requires-Dist: pydispatcher>=2.0.7
Requires-Dist: PyYAML>=5.1
Requires-Dist: openpyxl>=3.0
Requires-Dist: requests>=2.0
Requires-Dist: pandas>=2.0
Requires-Dist: traitlets-pcse==5.0.0.dev
Requires-Dist: dotmap>=1.3
Dynamic: license-file
